spectra_lexer/__init__.py
spectra_lexer/__main__.py
spectra_lexer/app_discord.py
spectra_lexer/app_json.py
spectra_lexer/app_plover.py
spectra_lexer/app_qt.py
spectra_lexer/engine.py
spectra_lexer/main_console.py
spectra_lexer/main_discord.py
spectra_lexer/main_http.py
spectra_lexer/main_index.py
spectra_lexer/main_qt.py
spectra_lexer/options.py
spectra_lexer/spc_board.py
spectra_lexer/spc_graph.py
spectra_lexer/spc_lexer.py
spectra_lexer/spc_resource.py
spectra_lexer/spc_search.py
spectra_lexer/spectra.py
spectra_lexer/assets/board_defs.cson
spectra_lexer/assets/key_layout.cson
spectra_lexer/assets/rules.cson
spectra_lexer/board/__init__.py
spectra_lexer/board/layout.py
spectra_lexer/board/path.py
spectra_lexer/board/svg.py
spectra_lexer/board/tfrm.py
spectra_lexer/config/__init__.py
spectra_lexer/config/io.py
spectra_lexer/config/main.py
spectra_lexer/config/parser.py
spectra_lexer/config/qt.py
spectra_lexer/config/spec.py
spectra_lexer/console/__init__.py
spectra_lexer/console/main.py
spectra_lexer/console/qt.py
spectra_lexer/console/system.py
spectra_lexer/discord/__init__.py
spectra_lexer/discord/backoff.py
spectra_lexer/discord/client.py
spectra_lexer/discord/event.py
spectra_lexer/discord/gateway.py
spectra_lexer/discord/http.py
spectra_lexer/discord/logger.py
spectra_lexer/discord/request.py
spectra_lexer/graph/__init__.py
spectra_lexer/graph/body.py
spectra_lexer/graph/canvas.py
spectra_lexer/graph/connectors.py
spectra_lexer/graph/format.py
spectra_lexer/graph/layout.py
spectra_lexer/graph/node.py
spectra_lexer/http/__init__.py
spectra_lexer/http/connect.py
spectra_lexer/http/json.py
spectra_lexer/http/request.py
spectra_lexer/http/response.py
spectra_lexer/http/service.py
spectra_lexer/http/status.py
spectra_lexer/http/tcp.py
spectra_lexer/http_public/icon.png
spectra_lexer/http_public/index.css
spectra_lexer/http_public/index.html
spectra_lexer/http_public/index.js
spectra_lexer/lexer/__init__.py
spectra_lexer/lexer/composite.py
spectra_lexer-16.1.0.dist-info/LICENSE.txt
spectra_lexer-16.1.0.dist-info/METADATA
spectra_lexer-16.1.0.dist-info/WHEEL
spectra_lexer-16.1.0.dist-info/entry_points.txt
spectra_lexer-16.1.0.dist-info/top_level.txt
spectra_lexer-16.1.0.dist-info/RECORD
