Metadata-Version: 2.1
Name: spectra-lexer
Version: 16.1.0
Summary: Stroke and rule analyzer for stenography
Home-page: https://github.com/fourshade/spectra_lexer
Author: fourshade
Author-email: synnethrelmn@yahoo.com
License: GNU General Public License v2 or later (GPLv2+)
Keywords: plover plover_plugin
Platform: UNKNOWN
Classifier: Development Status :: 4 - Beta
Classifier: Environment :: Plugins
Classifier: Intended Audience :: End Users/Desktop
Classifier: License :: OSI Approved :: GNU General Public License v2 or later (GPLv2+)
Classifier: Natural Language :: English
Classifier: Operating System :: OS Independent
Classifier: Programming Language :: Python :: 3
Classifier: Programming Language :: Python :: 3.6
Classifier: Programming Language :: Python :: 3.7
Classifier: Programming Language :: Python :: 3.8
Classifier: Programming Language :: Python :: 3.9
Classifier: Topic :: Text Processing :: Linguistic
Requires-Python: >=3.6
Requires-Dist: PyQt5 (>=5.5)
Provides-Extra: discord
Requires-Dist: aiohttp (==3.6.2) ; extra == 'discord'
